census_lookup/__init__.py
census_lookup/__main__.py
census_lookup/address/__init__.py
census_lookup/address/matcher.py
census_lookup/address/normalizer.py
census_lookup/address/parser.py
census_lookup/census/__init__.py
census_lookup/census/acs.py
census_lookup/census/variables.py
census_lookup/cli/__init__.py
census_lookup/cli/commands.py
census_lookup/core/__init__.py
census_lookup/core/geoid.py
census_lookup/core/lookup.py
census_lookup/core/spatial.py
census_lookup/data/__init__.py
census_lookup/data/catalog.py
census_lookup/data/constants.py
census_lookup/data/converter.py
census_lookup/data/downloader.py
census_lookup/data/duckdb_engine.py
census_lookup/data/manager.py
census_lookup/data/pl94171_parser.py
census_lookup/stubs/usaddress.pyi
census_lookup-0.2.3.dist-info/licenses/LICENSE
census_lookup-0.2.3.dist-info/METADATA
census_lookup-0.2.3.dist-info/WHEEL
census_lookup-0.2.3.dist-info/entry_points.txt
census_lookup-0.2.3.dist-info/top_level.txt
census_lookup-0.2.3.dist-info/RECORD
