Metadata-Version: 2.4
Name: census-lookup
Version: 0.2.3
Summary: Offline address-to-Census data mapping for Python with PL 94-171 and ACS support
Author: Harry Waye
License: MIT
Project-URL: Homepage, https://github.com/yolodex-ai/census-lookup
Project-URL: Repository, https://github.com/yolodex-ai/census-lookup
Project-URL: Issues, https://github.com/yolodex-ai/census-lookup/issues
Keywords: census,geocoding,gis,tiger,demographics,acs,pl94171
Classifier: Development Status :: 3 - Alpha
Classifier: Intended Audience :: Science/Research
Classifier: License :: OSI Approved :: MIT License
Classifier: Programming Language :: Python :: 3
Classifier: Programming Language :: Python :: 3.10
Classifier: Programming Language :: Python :: 3.11
Classifier: Programming Language :: Python :: 3.12
Classifier: Topic :: Scientific/Engineering :: GIS
Requires-Python: >=3.10
License-File: LICENSE
Requires-Dist: duckdb>=1.0.0
Requires-Dist: geopandas>=0.14.0
Requires-Dist: pandas>=2.0.0
Requires-Dist: shapely>=2.0.0
Requires-Dist: pyproj>=3.0.0
Requires-Dist: usaddress>=0.5.10
Requires-Dist: requests>=2.28.0
Requires-Dist: aiohttp>=3.9.0
Requires-Dist: click>=8.0.0
Requires-Dist: tqdm>=4.65.0
Requires-Dist: pyarrow>=12.0.0
Provides-Extra: dev
Requires-Dist: pytest>=7.0.0; extra == "dev"
Requires-Dist: pytest-asyncio>=0.23.0; extra == "dev"
Requires-Dist: pytest-cov>=4.0.0; extra == "dev"
Requires-Dist: pytest-xdist>=3.5.0; extra == "dev"
Requires-Dist: aioresponses>=0.7.0; extra == "dev"
Requires-Dist: ruff>=0.1.0; extra == "dev"
Requires-Dist: mypy>=1.0.0; extra == "dev"
Requires-Dist: pre-commit>=3.0.0; extra == "dev"
Dynamic: license-file
